FGFinder/FGFinder.py
FGFinder/__init__.py
FGFinder/__main__.py
FGFinder/data/fgsmarts.pkl
FGFinder-1.0.1.dist-info/LICENSE
FGFinder-1.0.1.dist-info/METADATA
FGFinder-1.0.1.dist-info/WHEEL
FGFinder-1.0.1.dist-info/top_level.txt
FGFinder-1.0.1.dist-info/RECORD
